README.md
setup.cfg
setup.py
bin/precipy
precipy/__init__.py
precipy/analytics_function.py
precipy/batch.py
precipy/identifiers.py
precipy/jinja_filters.py
precipy/main.py
precipy/mock.py
precipy/output_filters.py
precipy/storage.py
precipy.egg-info/PKG-INFO
precipy.egg-info/SOURCES.txt
precipy.egg-info/dependency_links.txt
precipy.egg-info/requires.txt
precipy.egg-info/top_level.txt
tests/__init__.py
tests/analytics.py
tests/test_analytics_function.py
tests/test_batch.py
tests/test_render.py
tests/test_storage.py