Metadata-Version: 2.1
Name: precipy
Version: 0.3.8
Summary: Lightweight document automation for analytics reporting.
Home-page: https://github.com/ananelson/precipy
Author: Ana Clarkson
Author-email: ana@zymocosm.com
License: UNKNOWN
Platform: UNKNOWN
Classifier: Programming Language :: Python :: 3
Classifier: Operating System :: OS Independent
